{
	"code": "glassladle",
	"class": "glassmaking:glassladle",
	"variantgroups": [
		{
			"code": "size",
			"states": [ "small", "medium", "large" ]
		}
	],
	"maxstacksize": 1,
	"creativeinventory": {
		"general": [ "*" ],
		"tools": [ "*" ],
		"glassmaking": [ "*" ]
	},
	"behaviors": [
		{
			"name": "GroundStorable",
			"properties": {
				"layout": "Halves",
				"collisionBox": { "x1": 0, "y1": 0, "z1": 0, "x2": 1, "y2": 0.125, "z2": 1 }
			}
		}
	],
  "attributes": {
		"groundTransformByType": {
			"*-small": {
        "translation": { "x": 0, "y": 0, "z": 0.2 },
        "origin": { "x": 0.5, "y": 0, "z": 0.5 },
        "scale": 0.65
      },
      "*-medium": {
        "translation": { "x": 0, "y": 0, "z": 0.18 },
        "origin": { "x": 0.5, "y": 0, "z": 0.5 },
        "scale": 0.65
      },
      "*-large": {
        "translation": { "x": 0, "y": 0, "z": 0.2 },
        "origin": { "x": 0.5, "y": 0, "z": 0.5 },
        "scale": 0.6
      }
		},
		"handbook": {
			"extraSections": [
				{
					"title": "glassmaking:handbook-glassblower-tools",
					"text": "glassmaking:item-handbooktext-glassladle"
				}
			]
		},
    "maxGlassByType": {
      "*-small": 250,
      "*-medium": 500,
      "*-large": 1000
    },
    "glassThresholdByType": {
      "*-small": 100,
      "*-medium": 200,
      "*-large": 400
    },
    "glassTransform": {
      "origin": { "x": 0.5, "y": 0, "z": 0.5 },
      "translation": { "y": 0.0625 },
      "scaleXYZByType": {
        "*-small": { "x": 0.375, "y": 0.25, "z": 0.375 },
        "*-medium": { "x": 0.5, "y": 0.3125, "z": 0.5 },
        "*-large": { "x": 0.75, "y": 0.4375, "z": 0.75 }
      },
      "rotation": { "y": 45 }
    },
    "takeTransform": {
      "origin": { "x": 0.5, "y": 0.2, "z": 0.5 },
      "translationByType": {
        "*-small": { "x": 0.75, "y": 0.4, "z": 0.5 },
        "*-medium": { "x": 0.4, "y": 0.4, "z": 0.5 },
        "*-large": { "x": 0, "y": 0.4, "z": 0.5 }
      },
      "rotation": { "x": -10, "y": 10, "z": -90 },
      "scale": 0.9
    },
    "pourTransform": {
      "origin": { "x": 0.5, "y": 0.2, "z": 0.5 },
      "translationByType": {
        "*-small": { "x": 0.75, "y": 0.4, "z": 0.5 },
        "*-medium": { "x": 0.3, "y": 0.5, "z": 0.5 },
        "*-large": { "x": -0.3, "y": 0.4, "z": 1 }
      },
      "rotationByType": {
        "*-small": { "x": -10, "y": 0, "z": -10 },
        "*-medium": { "x": -10, "y": -5, "z": -10 },
        "*-large": { "x": -10, "y": -10, "z": -10 }
      },
      "scaleByType": {
        "@.*-(small|medium)": 0.9,
        "*-large": 1.1
      }
    },
    "pourAnimationSpeedByType": { "*-large": 0.75 }
  },
	"heldTpIdleAnimation": "holdunderarm",
	"textures": {
		"glass": { "base": "game:item/resource/ungraded/quartz" }
	},
	"shape": { "base": "item/glassladle/{size}" },
	"tpHandTransform": {
		"translationByType": {
			"*-small": {
				"x": -2.75,
				"y": -1.2,
				"z": -1.2
			},
			"*-medium": {
				"x": -2.75,
				"y": -1.2,
				"z": -1.2
			},
			"*-large": {
				"x": -3.5,
				"y": -1.75,
				"z": -1.2
			}
		},
		"rotation": {
			"x": 85,
			"y": 120,
			"z": 80
		},
		"origin": {
			"x": 0.5,
			"y": 0.2,
			"z": 0.5
		},
		"scale": 0.4
	},
	"fpHandTransformByType": {
		"*-large": {
			"translation": {
				"x": -0.5,
				"y": 0.1,
				"z": -1.25
			},
			"rotation": {
				"x": -170,
				"y": -20,
				"z": 170
			},
			"origin": {
				"x": 0.5,
				"y": 0.2,
				"z": 0.5
			},
			"scale": 1.75
		},
		"*-medium": {
			"translation": {
				"x": -0.45,
				"y": 0.3,
				"z": -0.4
			},
			"rotation": {
				"x": -170,
				"y": -22,
				"z": 170
			},
			"origin": {
				"x": 0.5,
				"y": 0.2,
				"z": 0.5
			},
			"scale": 1.4
		},
		"*-small": {
			"translation": {
				"x": -0.3,
				"y": 0.4,
				"z": -0.5
			},
			"rotation": {
				"x": -170,
				"y": -15,
				"z": 170
			},
			"origin": {
				"x": 0.5,
				"y": 0.2,
				"z": 0.5
			},
			"scale": 1.3
		}
	},
	"guiTransform": {
		"rotation": {
			"x": 160,
			"y": -19,
			"z": 0
		},
		"origin": {
			"x": 0.5,
			"y": 0.2,
			"z": 0.15
		},
		"scaleByType": {
			"*-small": 1.5,
			"*-medium": 1.3,
			"*-large": 1.2
		}
	}
}